dtob/__init__.py
dtob-1.1.2.dist-info/METADATA
dtob-1.1.2.dist-info/WHEEL
dtob-1.1.2.dist-info/top_level.txt
dtob-1.1.2.dist-info/RECORD
