Metadata-Version: 2.1
Name: dtob
Version: 1.1.2
Summary: Convert dictionaries into objects with attribute-style access.
Home-page: https://github.com/husseinnaeemsec/dicttoobject
Author: Hussein Naeem
Author-email: husseinnaeemsec@gmail.com
License: MIT
Classifier: Programming Language :: Python :: 3
Classifier: License :: OSI Approved :: MIT License
Classifier: Operating System :: OS Independent
Requires-Python: >=3.6
